PyEncodeAI/__init__.py
PyEncodeAI/info.py
PyEncodeAI-0.0.3.dist-info/LICENSE
PyEncodeAI-0.0.3.dist-info/METADATA
PyEncodeAI-0.0.3.dist-info/WHEEL
PyEncodeAI-0.0.3.dist-info/top_level.txt
PyEncodeAI-0.0.3.dist-info/RECORD
