Metadata-Version: 2.1
Name: PyEncodeAI
Version: 0.0.3
Summary: Here gonna be something special ...
Home-page: https://github.com/urniaz/
Author: Rafal Urniaz
Classifier: Programming Language :: Python :: 3
Classifier: License :: OSI Approved :: GNU General Public License v3 (GPLv3)
Classifier: Operating System :: OS Independent
License-File: LICENSE
